microbootstrap/__init__.py
microbootstrap/bootstrappers/__init__.py
microbootstrap/bootstrappers/base.py
microbootstrap/bootstrappers/fastapi.py
microbootstrap/bootstrappers/faststream.py
microbootstrap/bootstrappers/litestar.py
microbootstrap/config/__init__.py
microbootstrap/config/fastapi.py
microbootstrap/config/faststream.py
microbootstrap/config/litestar.py
microbootstrap/console_writer.py
microbootstrap/exceptions.py
microbootstrap/granian_server.py
microbootstrap/helpers.py
microbootstrap/instruments/__init__.py
microbootstrap/instruments/base.py
microbootstrap/instruments/cors_instrument.py
microbootstrap/instruments/health_checks_instrument.py
microbootstrap/instruments/instrument_box.py
microbootstrap/instruments/logging_instrument.py
microbootstrap/instruments/opentelemetry_instrument.py
microbootstrap/instruments/prometheus_instrument.py
microbootstrap/instruments/pyroscope_instrument.py
microbootstrap/instruments/sentry_instrument.py
microbootstrap/instruments/swagger_instrument.py
microbootstrap/instruments_setupper.py
microbootstrap/middlewares/__init__.py
microbootstrap/middlewares/fastapi.py
microbootstrap/middlewares/litestar.py
microbootstrap/py.typed
microbootstrap/settings.py
microbootstrap-1.1.0.dist-info/WHEEL
microbootstrap-1.1.0.dist-info/METADATA
microbootstrap-1.1.0.dist-info/RECORD
