Metadata-Version: 2.3
Name: microbootstrap
Version: 1.1.0
Summary: Package for bootstrapping new micro-services
Keywords: python,microservice,bootstrap,opentelemetry,logging,error-tracing,litestar,fastapi
Author: community-of-python
Classifier: Typing :: Typed
Classifier: Topic :: Software Development :: Build Tools
Classifier: Operating System :: MacOS
Classifier: Operating System :: Microsoft
Classifier: Operating System :: POSIX :: Linux
Classifier: Intended Audience :: Developers
Classifier: Programming Language :: Python
Classifier: Programming Language :: Python :: 3
Classifier: Programming Language :: Python :: 3 :: Only
Classifier: Programming Language :: Python :: 3.10
Classifier: Programming Language :: Python :: 3.11
Classifier: Programming Language :: Python :: 3.12
Classifier: Programming Language :: Python :: 3.13
Classifier: Programming Language :: Python :: 3.14
Requires-Dist: eval-type-backport>=0.2
Requires-Dist: opentelemetry-api>=1.30.0
Requires-Dist: opentelemetry-exporter-otlp>=1.15.0
Requires-Dist: opentelemetry-exporter-prometheus-remote-write>=0.46b0
Requires-Dist: opentelemetry-instrumentation>=0.46b0
Requires-Dist: opentelemetry-instrumentation-system-metrics>=0.46b0
Requires-Dist: opentelemetry-sdk>=1.30.0
Requires-Dist: pydantic-settings>=2
Requires-Dist: rich>=13
Requires-Dist: sentry-sdk>=2.7
Requires-Dist: structlog>=24
Requires-Dist: pyroscope-io ; sys_platform != 'win32'
Requires-Dist: opentelemetry-distro[otlp]>=0.54b1
Requires-Dist: opentelemetry-instrumentation-aio-pika>=0.54b1
Requires-Dist: opentelemetry-instrumentation-aiohttp-client>=0.54b1
Requires-Dist: opentelemetry-instrumentation-aiokafka>=0.54b1
Requires-Dist: opentelemetry-instrumentation-asyncpg>=0.54b1
Requires-Dist: opentelemetry-instrumentation-httpx>=0.54b1
Requires-Dist: opentelemetry-instrumentation-logging>=0.54b1
Requires-Dist: opentelemetry-instrumentation-redis>=0.54b1
Requires-Dist: opentelemetry-instrumentation-psycopg>=0.54b1
Requires-Dist: opentelemetry-instrumentation-sqlalchemy>=0.54b1
Requires-Dist: opentelemetry-instrumentation-asyncio>=0.54b1
Requires-Dist: opentelemetry-instrumentation-asgi>=0.46b0
Requires-Dist: orjson>=3.10.18
Requires-Dist: fastapi>=0.100 ; extra == 'fastapi'
Requires-Dist: fastapi-offline-docs>=1 ; extra == 'fastapi'
Requires-Dist: opentelemetry-instrumentation-fastapi>=0.46b0 ; extra == 'fastapi'
Requires-Dist: prometheus-fastapi-instrumentator>=6.1 ; extra == 'fastapi'
Requires-Dist: faststream~=0.6.2 ; extra == 'faststream'
Requires-Dist: prometheus-client>=0.20 ; extra == 'faststream'
Requires-Dist: granian[reload]>=1 ; extra == 'granian'
Requires-Dist: litestar>=2.9 ; extra == 'litestar'
Requires-Dist: litestar-offline-docs>=1 ; extra == 'litestar'
Requires-Dist: prometheus-client>=0.20 ; extra == 'litestar'
Requires-Python: >=3.10, <4
Provides-Extra: fastapi
Provides-Extra: faststream
Provides-Extra: granian
Provides-Extra: litestar
